odoo/addons/base_geoengine/README.rst
odoo/addons/base_geoengine/__init__.py
odoo/addons/base_geoengine/__manifest__.py
odoo/addons/base_geoengine/fields.py
odoo/addons/base_geoengine/geo_db.py
odoo/addons/base_geoengine/geo_model.py
odoo/addons/base_geoengine/geo_operators.py
odoo/addons/base_geoengine/doc/Makefile
odoo/addons/base_geoengine/doc/make.bat
odoo/addons/base_geoengine/doc/build/.buildinfo
odoo/addons/base_geoengine/doc/build/api_doc.html
odoo/addons/base_geoengine/doc/build/genindex.html
odoo/addons/base_geoengine/doc/build/index.html
odoo/addons/base_geoengine/doc/build/installation.html
odoo/addons/base_geoengine/doc/build/objects.inv
odoo/addons/base_geoengine/doc/build/postgisify.html
odoo/addons/base_geoengine/doc/build/prerequisite.html
odoo/addons/base_geoengine/doc/build/py-modindex.html
odoo/addons/base_geoengine/doc/build/search.html
odoo/addons/base_geoengine/doc/build/searchindex.js
odoo/addons/base_geoengine/doc/build/what_is_geoengine.html
odoo/addons/base_geoengine/doc/build/.doctrees/api_doc.doctree
odoo/addons/base_geoengine/doc/build/.doctrees/environment.pickle
odoo/addons/base_geoengine/doc/build/.doctrees/index.doctree
odoo/addons/base_geoengine/doc/build/.doctrees/installation.doctree
odoo/addons/base_geoengine/doc/build/.doctrees/postgisify.doctree
odoo/addons/base_geoengine/doc/build/.doctrees/prerequisite.doctree
odoo/addons/base_geoengine/doc/build/.doctrees/what_is_geoengine.doctree
odoo/addons/base_geoengine/doc/build/.doctrees/_templates/prerequisite.doctree
odoo/addons/base_geoengine/doc/build/_images/core_architecture.jpg
odoo/addons/base_geoengine/doc/build/_sources/api_doc.txt
odoo/addons/base_geoengine/doc/build/_sources/index.txt
odoo/addons/base_geoengine/doc/build/_sources/installation.txt
odoo/addons/base_geoengine/doc/build/_sources/postgisify.txt
odoo/addons/base_geoengine/doc/build/_sources/prerequisite.txt
odoo/addons/base_geoengine/doc/build/_sources/what_is_geoengine.txt
odoo12_addon_base_geoengine-12.0.1.3.0.dist-info/METADATA
odoo12_addon_base_geoengine-12.0.1.3.0.dist-info/WHEEL
odoo12_addon_base_geoengine-12.0.1.3.0.dist-info/top_level.txt
odoo12_addon_base_geoengine-12.0.1.3.0.dist-info/RECORD
