Metadata-Version: 2.1
Name: odoo12-addon-base-geoengine
Version: 12.0.1.3.0
Summary: Geospatial support for Odoo
Home-page: https://github.com/OCA/geospatial
Author: Camptocamp,ACSONE SA/NV,Odoo Community Association (OCA)
Author-email: support@odoo-community.org
License: AGPL-3
Platform: UNKNOWN
Classifier: Programming Language :: Python
Classifier: Framework :: Odoo
Classifier: Framework :: Odoo :: 12.0
Classifier: License :: OSI Approved :: GNU Affero General Public License v3
Requires-Python: >=3.5
Requires-Dist: geojson
Requires-Dist: odoo <12.1dev,>=12.0a
Requires-Dist: shapely
Requires-Dist: simplejson
